wordfilegenerator/__init__.py
wordfilegenerator/main.py
wordfilegenerator-3.0.0.dist-info/LICENSE.txt
wordfilegenerator-3.0.0.dist-info/METADATA
wordfilegenerator-3.0.0.dist-info/WHEEL
wordfilegenerator-3.0.0.dist-info/top_level.txt
wordfilegenerator-3.0.0.dist-info/RECORD
