Metadata-Version: 2.1
Name: wordfilegenerator
Version: 3.0.0
Summary: Generate custom wordlists for brute force testing.
Author: Sandru
Author-email: sandrusimsone13579@gmail.com
License: MIT
Classifier: Programming Language :: Python :: 3
Classifier: License :: OSI Approved :: MIT License
Classifier: Operating System :: OS Independent
Requires-Python: >=3.6
License-File: LICENSE.txt
